AUTHORS.rst
CONTRIBUTING.rst
HISTORY.rst
LICENSE
MANIFEST.in
README.rst
setup.cfg
setup.py
docs/Makefile
docs/authors.rst
docs/conf.py
docs/contributing.rst
docs/history.rst
docs/index.rst
docs/installation.rst
docs/make.bat
docs/readme.rst
docs/usage.rst
helloworldtest/__init__.py
helloworldtest/cli.py
helloworldtest/helloworldtest.py
helloworldtest.egg-info/PKG-INFO
helloworldtest.egg-info/SOURCES.txt
helloworldtest.egg-info/dependency_links.txt
helloworldtest.egg-info/entry_points.txt
helloworldtest.egg-info/not-zip-safe
helloworldtest.egg-info/requires.txt
helloworldtest.egg-info/top_level.txt
tests/__init__.py
tests/test_helloworldtest.py